i2net/__init__.py
i2net/i2net.py
i2net-2.6.1.dist-info/licenses/LICENSE
i2net-2.6.1.dist-info/METADATA
i2net-2.6.1.dist-info/WHEEL
i2net-2.6.1.dist-info/top_level.txt
i2net-2.6.1.dist-info/RECORD
