Metadata-Version: 2.4
Name: i2net
Version: 2.6.1
Summary: I2NeT (Images to Network Traffic), extract and reconstruct data from RGB-encoded PNG images into CSV format. Suitable for CNN-based anomaly detection.
Author-email: Omesh Fernando <omeshf@gmail.com>
License-Expression: MIT
Project-URL: Homepage, https://github.com/omeshF/I2NeT
Project-URL: Issues, https://github.com/omeshF/I2NeT/issues
Project-URL: Documentation, https://github.com/omeshF/I2NeT#readme
Classifier: Programming Language :: Python :: 3
Classifier: Operating System :: OS Independent
Classifier: Topic :: Security
Classifier: Topic :: Scientific/Engineering :: Artificial Intelligence
Classifier: Intended Audience :: Science/Research
Classifier: Intended Audience :: Developers
Classifier: Development Status :: 4 - Beta
Requires-Python: >=3.9
License-File: LICENSE
Dynamic: license-file
